MANIFEST.in
README.txt
setup.py
update.sh
mwlib/__init__.py
mwlib/_extversion.py
mwlib.ext.egg-info/PKG-INFO
mwlib.ext.egg-info/SOURCES.txt
mwlib.ext.egg-info/dependency_links.txt
mwlib.ext.egg-info/namespace_packages.txt
mwlib.ext.egg-info/not-zip-safe
mwlib.ext.egg-info/top_level.txt
mwlib/ext/__init__.py
upstream-src/CHANGES.txt
upstream-src/INSTALL.txt
upstream-src/LICENSE.txt
upstream-src/README.txt
upstream-src/VERSION.txt
upstream-src/ez_setup.py
upstream-src/setup.cfg
upstream-src/setup.py
upstream-src/demos/colors/colortest.py
upstream-src/demos/gadflypaper/00readme.txt
upstream-src/demos/gadflypaper/gfe.py
upstream-src/demos/odyssey/00readme.txt
upstream-src/demos/odyssey/dodyssey.py
upstream-src/demos/odyssey/fodyssey.py
upstream-src/demos/odyssey/odyssey.py
upstream-src/demos/odyssey/odyssey.txt
upstream-src/demos/rlzope/readme.txt
upstream-src/demos/rlzope/rlzope.py
upstream-src/demos/stdfonts/00readme.txt
upstream-src/demos/stdfonts/stdfonts.py
upstream-src/demos/tests/testdemos.py
upstream-src/docs/00readme.txt
upstream-src/docs/Makefile
upstream-src/docs/genAll.py
upstream-src/docs/gen_epydoc
upstream-src/docs/make.bat
upstream-src/docs/images/Edit_Prefs.gif
upstream-src/docs/images/Python_21.gif
upstream-src/docs/images/Python_21_HINT.gif
upstream-src/docs/images/fileExchange.gif
upstream-src/docs/images/jpn.gif
upstream-src/docs/images/jpnchars.jpg
upstream-src/docs/images/lj8100.jpg
upstream-src/docs/images/redsquare.png
upstream-src/docs/images/replogo.a85
upstream-src/docs/images/replogo.gif
upstream-src/docs/images/testimg.gif
upstream-src/docs/reference/build.bat
upstream-src/docs/reference/genreference.py
upstream-src/docs/reference/reference.yml
upstream-src/docs/source/conf.py
upstream-src/docs/source/graphics.rst
upstream-src/docs/source/index.rst
upstream-src/docs/source/lib.rst
upstream-src/docs/source/pdfgen.rst
upstream-src/docs/source/platypus.rst
upstream-src/docs/source/_static/basic.css
upstream-src/docs/source/_static/default.css
upstream-src/docs/source/_templates/layout.html
upstream-src/docs/source/_templates/page.html
upstream-src/docs/userguide/app_demos.py
upstream-src/docs/userguide/ch1_intro.py
