Metadata-Version: 1.0
Name: mwlib.ext
Version: 0.13.2
Summary: provide dependencies for mwlib
Home-page: http://code.pediapress.com/
Author: pediapress.com
Author-email: info@pediapress.com
License: BSD License
Platform: UNKNOWN
